metacells-0.9.5.data/headers/extensions.h
metacells/prune_per.cpp
metacells/py.typed
metacells/cover.cpp
metacells/shuffle.cpp
metacells/downsample.cpp
metacells/logistics.cpp
metacells/auroc.cpp
metacells/partitions.cpp
metacells/__init__.py
metacells/choose_seeds.cpp
metacells/correlate.cpp
metacells/should_check_avx2.py
metacells/check_avx2.py
metacells/rank.cpp
metacells/gaps.cpp
metacells/relayout.cpp
metacells/extensions.cpython-310-x86_64-linux-gnu.so
metacells/extensions.cpp
metacells/folds.cpp
metacells/parameters.py
metacells/top_per.cpp
metacells/extensions.h
metacells/utilities/py.typed
metacells/utilities/timing.py
metacells/utilities/__init__.py
metacells/utilities/progress.py
metacells/utilities/logging.py
metacells/utilities/annotation.py
metacells/utilities/parallel.py
metacells/utilities/typing.py
metacells/utilities/computation.py
metacells/utilities/documentation.py
metacells/pipeline/select.py
metacells/pipeline/collect.py
metacells/pipeline/mark.py
metacells/pipeline/divide_and_conquer.py
metacells/pipeline/__init__.py
metacells/pipeline/related_genes.py
metacells/pipeline/exclude.py
metacells/pipeline/direct.py
metacells/pipeline/mcview.py
metacells/pipeline/projection.py
metacells/pipeline/umap.py
metacells/tools/candidates.py
metacells/tools/convey.py
metacells/tools/properly_sampled.py
metacells/tools/rare.py
metacells/tools/downsample.py
metacells/tools/deviants.py
metacells/tools/__init__.py
metacells/tools/similarity.py
metacells/tools/quality.py
metacells/tools/knn_graph.py
metacells/tools/apply.py
metacells/tools/bursty_lonely.py
metacells/tools/distinct.py
metacells/tools/mask.py
metacells/tools/group.py
metacells/tools/filter.py
metacells/tools/layout.py
metacells/tools/named.py
metacells/tools/high.py
metacells/tools/dissolve.py
metacells/tools/project.py
metacells/scripts/timing.py
metacells/scripts/__init__.py
metacells-0.9.5.dist-info/METADATA
metacells-0.9.5.dist-info/entry_points.txt
metacells-0.9.5.dist-info/LICENSE.rst
metacells-0.9.5.dist-info/RECORD
metacells-0.9.5.dist-info/top_level.txt
metacells-0.9.5.dist-info/WHEEL
