Metadata-Version: 2.1
Name: metacells
Version: 0.9.5
Summary: Single-cell RNA Sequencing Analysis
Home-page: https://github.com/tanaylab/metacells.git
Author: Oren Ben-Kiki
Author-email: oren@ben-kiki.org
License: MIT license
Keywords: metacells
Classifier: Development Status :: 4 - Beta
Classifier: Intended Audience :: Developers
Classifier: Natural Language :: English
Classifier: Programming Language :: Python :: 3
Classifier: Programming Language :: Python :: 3.7
Classifier: Programming Language :: Python :: 3.8
Classifier: Programming Language :: Python :: 3.9
Classifier: Programming Language :: Python :: 3.10
Classifier: Programming Language :: Python :: 3.11
Classifier: Programming Language :: Python :: 3.12
Classifier: Topic :: Software Development :: Libraries
Classifier: Topic :: Scientific/Engineering :: Bio-Informatics
Classifier: Intended Audience :: Developers
Classifier: Intended Audience :: Science/Research
Requires-Python: >=3.7
License-File: LICENSE.rst
Requires-Dist: anndata
Requires-Dist: cvxpy
Requires-Dist: fastcluster
Requires-Dist: importlib-metadata
Requires-Dist: numpy
Requires-Dist: pandas
Requires-Dist: psutil
Requires-Dist: python-igraph
Requires-Dist: pyyaml
Requires-Dist: scanpy
Requires-Dist: scipy
Requires-Dist: threadpoolctl
Requires-Dist: umap-learn
Provides-Extra: dev
Requires-Dist: black ; extra == 'dev'
Requires-Dist: bumpversion ; extra == 'dev'
Requires-Dist: flake8 ; extra == 'dev'
Requires-Dist: isort ; extra == 'dev'
Requires-Dist: mypy ; extra == 'dev'
Requires-Dist: mypy-extensions ; extra == 'dev'
Requires-Dist: pandas-stubs ; extra == 'dev'
Requires-Dist: pylint ; extra == 'dev'
Requires-Dist: pytest ; extra == 'dev'
Requires-Dist: pytest-cov ; extra == 'dev'
Requires-Dist: sphinx ; extra == 'dev'
Requires-Dist: sphinx-rtd-theme ; extra == 'dev'
Requires-Dist: twine ; extra == 'dev'
Requires-Dist: tox ; extra == 'dev'
